MEROAI/__init__.py
MEROAI/activations.py
MEROAI/activations_tf.py
MEROAI/audio_utils.py
MEROAI/cache_utils.py
MEROAI/configuration_utils.py
MEROAI/convert_graph_to_onnx.py
MEROAI/convert_slow_tokenizer.py
MEROAI/convert_slow_tokenizers_checkpoints_to_fast.py
MEROAI/convert_tf_hub_seq_to_seq_bert_to_pytorch.py
MEROAI/debug_utils.py
MEROAI/dependency_versions_check.py
MEROAI/dependency_versions_table.py
MEROAI/dynamic_module_utils.py
MEROAI/feature_extraction_sequence_utils.py
MEROAI/feature_extraction_utils.py
MEROAI/file_utils.py
MEROAI/hf_argparser.py
MEROAI/hyperparameter_search.py
MEROAI/image_processing_base.py
MEROAI/image_processing_utils.py
MEROAI/image_processing_utils_fast.py
MEROAI/image_transforms.py
MEROAI/image_utils.py
MEROAI/keras_callbacks.py
MEROAI/masking_utils.py
MEROAI/model_debugging_utils.py
MEROAI/modelcard.py
MEROAI/modeling_attn_mask_utils.py
MEROAI/modeling_flash_attention_utils.py
MEROAI/modeling_flax_outputs.py
MEROAI/modeling_flax_pytorch_utils.py
MEROAI/modeling_flax_utils.py
MEROAI/modeling_gguf_pytorch_utils.py
MEROAI/modeling_layers.py
MEROAI/modeling_outputs.py
MEROAI/modeling_rope_utils.py
MEROAI/modeling_tf_outputs.py
MEROAI/modeling_tf_pytorch_utils.py
MEROAI/modeling_tf_utils.py
MEROAI/modeling_utils.py
MEROAI/optimization.py
MEROAI/optimization_tf.py
MEROAI/processing_utils.py
MEROAI/py.typed
MEROAI/pytorch_utils.py
MEROAI/safetensors_conversion.py
MEROAI/testing_utils.py
MEROAI/tf_utils.py
MEROAI/time_series_utils.py
MEROAI/tokenization_mistral_common.py
MEROAI/tokenization_utils.py
MEROAI/tokenization_utils_base.py
MEROAI/tokenization_utils_fast.py
MEROAI/trainer.py
MEROAI/trainer_callback.py
MEROAI/trainer_pt_utils.py
MEROAI/trainer_seq2seq.py
MEROAI/trainer_utils.py
MEROAI/training_args.py
MEROAI/training_args_seq2seq.py
MEROAI/training_args_tf.py
MEROAI/video_processing_utils.py
MEROAI/video_utils.py
MEROAI/web_server.py
MEROAI/commands/__init__.py
MEROAI/commands/add_fast_image_processor.py
meroai-0.2.1.dist-info/licenses/LICENSE
meroai-0.2.1.dist-info/METADATA
meroai-0.2.1.dist-info/WHEEL
meroai-0.2.1.dist-info/entry_points.txt
meroai-0.2.1.dist-info/top_level.txt
meroai-0.2.1.dist-info/RECORD
