Metadata-Version: 2.4
Name: MEROAI
Version: 0.2.1
Summary: AI Programming Assistant for Code Analysis, Fixing, and Image Processing
Home-page: https://github.com/6x-u
Author: MERO
Author-email: MERO <MERO@ps.dev>
Maintainer-email: MERO <MERO@ps.dev>
License: MIT
Project-URL: Homepage, https://github.com/6x-u/MEROAI
Project-URL: Repository, https://github.com/6x-u/MEROAI
Project-URL: Documentation, https://github.com/6x-u/MEROAI#readme
Project-URL: Issues, https://github.com/6x-u/MEROAI/issues
Keywords: ai,programming,assistant,code-analysis,code-fixing,image-analysis,python,javascript,typescript,multilingual,arabic,english,mero,meroai
Classifier: Development Status :: 4 - Beta
Classifier: Intended Audience :: Developers
Classifier: License :: OSI Approved :: MIT License
Classifier: Operating System :: OS Independent
Classifier: Programming Language :: Python :: 3
Classifier: Programming Language :: Python :: 3.6
Classifier: Programming Language :: Python :: 3.7
Classifier: Programming Language :: Python :: 3.8
Classifier: Programming Language :: Python :: 3.9
Classifier: Programming Language :: Python :: 3.10
Classifier: Programming Language :: Python :: 3.11
Classifier: Programming Language :: Python :: 3.12
Classifier: Programming Language :: Python :: 3.13
Classifier: Programming Language :: Python :: 3.14
Classifier: Programming Language :: Python :: 3.15
Classifier: Topic :: Software Development :: Libraries :: Python Modules
Classifier: Topic :: Software Development :: Code Generators
Classifier: Topic :: Text Processing :: Linguistic
Classifier: Natural Language :: Arabic
Classifier: Natural Language :: English
Requires-Python: >=3.6.0
License-File: LICENSE
Requires-Dist: Pillow>=10.0.0
Requires-Dist: requests>=2.25.0
Provides-Extra: ai
Requires-Dist: openai>=1.0.0; extra == "ai"
Provides-Extra: full
Requires-Dist: openai>=1.0.0; extra == "full"
Requires-Dist: Pillow>=10.0.0; extra == "full"
Requires-Dist: requests>=2.25.0; extra == "full"
Provides-Extra: dev
Requires-Dist: pytest>=7.0.0; extra == "dev"
Requires-Dist: black>=22.0.0; extra == "dev"
Requires-Dist: flake8>=4.0.0; extra == "dev"
Dynamic: author
Dynamic: home-page
Dynamic: license-file
Dynamic: requires-python
